README.md
setup.py
wuhan_stats/__init__.py
wuhan_stats/__main__.py
wuhan_stats.egg-info/PKG-INFO
wuhan_stats.egg-info/SOURCES.txt
wuhan_stats.egg-info/dependency_links.txt
wuhan_stats.egg-info/requires.txt
wuhan_stats.egg-info/top_level.txt
wuhan_stats/src/__init__.py
wuhan_stats/src/app.py
wuhan_stats/src/site.py
wuhan_stats/src/utils.py