Metadata-Version: 2.1
Name: wuhan-stats
Version: 2.0
Summary: Simple desktop alert for Wuhan virus statistics updates
Home-page: https://github.com/vipervit/wuhan_stats
Author: vipervit
Author-email: vitolg1@gmail.com
License: Apache
Platform: UNKNOWN
Classifier: Programming Language :: Python :: 3
Classifier: License :: OSI Approved :: Apache Software License
Classifier: Operating System :: Microsoft :: Windows :: Windows 10
Classifier: Operating System :: MacOS :: MacOS X
Classifier: Development Status :: 4 - Beta
Classifier: Intended Audience :: End Users/Desktop
